Trinnuty/Trinnuty.py
Trinnuty/__init__.py
Trinnuty-0.0.1.dist-info/METADATA
Trinnuty-0.0.1.dist-info/WHEEL
Trinnuty-0.0.1.dist-info/top_level.txt
Trinnuty-0.0.1.dist-info/RECORD
